trainscribe/__init__.py
trainscribe/main.py
trainscribe-0.1.2.dist-info/WHEEL
trainscribe-0.1.2.dist-info/entry_points.txt
trainscribe-0.1.2.dist-info/METADATA
trainscribe-0.1.2.dist-info/RECORD
