Metadata-Version: 2.4
Name: trainscribe
Version: 0.1.2
Summary: A command-line tool for transcribing audio files in a folder to a metadata.csv file, using OpenAI's Whisper.
Keywords: transcribe,transcription,audio-transcription,openai-whisper,whisper,ljspeech,ljspeech-format,audio-formatter,text-to-speech,tts,tts-train,tts-finetune,cli,command-line
Author: VERA LVX
Author-email: VERA LVX <veralvx@veralvx.com>
License-Expression: MIT
Classifier: Development Status :: 4 - Beta
Classifier: Environment :: Console
Classifier: Intended Audience :: Developers
Classifier: License :: OSI Approved :: MIT License
Classifier: Natural Language :: English
Classifier: Operating System :: OS Independent
Classifier: Programming Language :: Python :: 3
Classifier: Programming Language :: Python :: 3 :: Only
Classifier: Programming Language :: Python :: 3.10
Classifier: Programming Language :: Python :: 3.11
Classifier: Programming Language :: Python :: 3.12
Classifier: Programming Language :: Python :: 3.13
Classifier: Programming Language :: Python :: Implementation :: CPython
Classifier: Topic :: Multimedia :: Sound/Audio :: Speech
Classifier: Topic :: Scientific/Engineering :: Artificial Intelligence
Classifier: Topic :: Text Processing
Classifier: Topic :: Text Processing :: General
Classifier: Topic :: Text Processing :: Linguistic
Classifier: Topic :: Utilities
Classifier: Typing :: Typed
Requires-Dist: devicer>=0.1.1
Requires-Dist: openai-whisper>=20250625
Requires-Dist: torch>=2.5.1
Requires-Dist: intel-extension-for-pytorch>=2.8,<3.0 ; python_full_version >= '3.10' and python_full_version < '3.14' and extra == 'xpu'
Maintainer: VERA LVX
Maintainer-email: VERA LVX <veralvx@veralvx.com>
Requires-Python: >=3.10, <3.14
Project-URL: Documentation, https://github.com/veralvx/trainscribe
Project-URL: Homepage, https://github.com/veralvx/trainscribe
Project-URL: Issues, https://github.com/veralvx/trainscribe/issues
Project-URL: Repository, https://github.com/veralvx/trainscribe
Provides-Extra: xpu
